questgen/__init__.py
questgen/actions.py
questgen/analysers.py
questgen/examples.py
questgen/exceptions.py
questgen/facts.py
questgen/graph_drawer.py
questgen/knowledge_base.py
questgen/logic.py
questgen/machine.py
questgen/quests/__init__.py
questgen/quests/base_quest.py
questgen/quests/caravan.py
questgen/quests/collect_debt.py
questgen/quests/complex.py
questgen/quests/delivery.py
questgen/quests/help.py
questgen/quests/help_friend.py
questgen/quests/hometown.py
questgen/quests/hunt.py
questgen/quests/interfere_enemy.py
questgen/quests/pilgrimage.py
questgen/quests/quests_base.py
questgen/quests/search_smith.py
questgen/quests/simple.py
questgen/quests/simplest.py
questgen/quests/spying.py
questgen/records.py
questgen/relations.py
questgen/requirements.py
questgen/restrictions.py
questgen/selectors.py
questgen/tests/__init__.py
questgen/tests/actions_tests.py
questgen/tests/facts_tests.py
questgen/tests/helpers.py
questgen/tests/knowledge_base_tests.py
questgen/tests/machine_tests.py
questgen/tests/quest_tests.py
questgen/tests/records_tests.py
questgen/tests/requirements_tests.py
questgen/tests/restrictions_tests.py
questgen/tests/selectors_tests.py
questgen/tests/simple_quest_tests.py
questgen/tests/transformators_tests.py
questgen/transformators.py
questgen/utils.py
questgen-0.4.2.dist-info/LICENSE
questgen-0.4.2.dist-info/WHEEL
questgen-0.4.2.dist-info/METADATA
questgen-0.4.2.dist-info/RECORD
